nonebot_plugin_follow_withdraw/__init__.py
nonebot_plugin_follow_withdraw/adapter.py
nonebot_plugin_follow_withdraw/adapters/__init__.py
nonebot_plugin_follow_withdraw/adapters/discord.py
nonebot_plugin_follow_withdraw/adapters/kaiheila.py
nonebot_plugin_follow_withdraw/adapters/onebot.py
nonebot_plugin_follow_withdraw/adapters/qqguild.py
nonebot_plugin_follow_withdraw/config.py
nonebot_plugin_follow_withdraw/migrations/258421aeb463_.py
nonebot_plugin_follow_withdraw/model.py
nonebot_plugin_follow_withdraw-0.2.0.dist-info/LICENSE
nonebot_plugin_follow_withdraw-0.2.0.dist-info/METADATA
nonebot_plugin_follow_withdraw-0.2.0.dist-info/WHEEL
nonebot_plugin_follow_withdraw-0.2.0.dist-info/RECORD
