Metadata-Version: 2.1
Name: nonebot-plugin-follow-withdraw
Version: 0.2.0
Summary: A plugin for nonebot2 that follows the user's withdraw of a command.
License: MIT
Author: CMHopeSunshine
Author-email: 277073121@qq.com
Requires-Python: >=3.8,<4.0
Classifier: License :: OSI Approved :: MIT License
Classifier: Programming Language :: Python :: 3
Classifier: Programming Language :: Python :: 3.8
Classifier: Programming Language :: Python :: 3.9
Classifier: Programming Language :: Python :: 3.10
Classifier: Programming Language :: Python :: 3.11
Requires-Dist: nonebot-plugin-datastore (>=1.0.0,<2.0.0)
Requires-Dist: nonebot2 (>=2.0.0,<3.0.0)
